DDSTAV/__init__.py
DDSTAV/app_web.py
DDSTAV/core.py
DDSTAV/ui.py
ddstav-0.1.0.dist-info/METADATA
ddstav-0.1.0.dist-info/WHEEL
ddstav-0.1.0.dist-info/licenses/LICENSE
ddstav-0.1.0.dist-info/RECORD
