Metadata-Version: 2.4
Name: DDSTAV
Version: 0.1.0
Summary: Document data structure type analyzer and vizualizer
Author: Ondrej Cánik
License-Expression: MIT
License-File: LICENSE
Classifier: Operating System :: OS Independent
Classifier: Programming Language :: Python :: 3
Requires-Python: >=3.9
Requires-Dist: matplotlib>=3.7
Requires-Dist: numpy>=1.23
Requires-Dist: pymongo>=4.6
Requires-Dist: seaborn>=0.12
